project/designual.vhd
library IEEE;
use IEEE.std_logic_1164.all;
use IEEE.numeric_std.all;
use IEEE.std_logic_unsigned.all;

entity ual is
    port(
        A_in: in std_logic_vector(3 downto 0);
        B_in: in std_logic_vector(3 downto 0);
        SR_in_L: in std_logic;
        SR_in_R: in std_logic;
        SEL_FCT: in std_logic_vector(3 downto 0);
        SR_out_L: out std_logic;
        SR_out_R: out std_logic;
        S_out: out std_logic_vector(7 downto 0)
    
);
end ual;

architecture ual_dataflow of ual is
    begin
        process(A_in, B_in, SEL_FCT, SR_in_L, SR_in_R)
        begin
            S_out <= (others => '0');
            case SEL_FCT is
            when "0000" => -- nop (no operation)
            S_out <= (others => '0');
            SR_out_L <= '0';
            SR_out_R <= '0';
            when "0001" => -- S=A SR_OUT_L=0etSR_OUT_R=0
            S_out(3 downto 0) <= A_in;
            SR_out_L <= '0';
            SR_out_R <= '0';
            when "0010" => -- S=B SR_OUT_L=0etSR_OUT_R=0
            S_out(3 downto 0) <= B_in;
            SR_out_L <= '0';
            SR_out_R <= '0';
            when "0011" => -- S=notA|SR_OUT_L=0etSR_OUT_R=0
            S_out(3 downto 0) <= not A_in;
            SR_out_L <= '0';
            SR_out_R <= '0';
            when "0100" => -- S=notB SR_OUT_L=0etSR_OUT_R=0
            S_out(3 downto 0) <= not B_in;
            SR_out_L <= '0';
            SR_out_R <= '0';
            when "0101" => -- S=A&B SR_OUT_L=0etSR_OUT_R=0
            S_out(3 downto 0) <= A_in and B_in;
            SR_out_L <= '0';
            SR_out_R <= '0';
            when "0110" => -- S=AorB|SR_OUT_L=0etSR_OUT_R=0
            S_out(3 downto 0) <= A_in or B_in;
            SR_out_L <= '0';
            SR_out_R <= '0';
            when "0111" => -- S=A xor B SR_OUT_L=0etSR_OUT_R=0
            S_out(3 downto 0) <= A_in xor B_in;
            SR_out_L <= '0';
            SR_out_R <= '0';
            when "1000" => -- S = Right shift A (avec SR_IN_L)
            S_out(3 downto 0) <= '0' & A_in(3 downto 1);
            SR_out_R <= A_in(0);
            SR_out_L <= '0' or SR_in_L;
            when "1001" => -- S = Left shift A (avec SR_IN_R)
            S_out(3 downto 1) <= A_in(2 downto 0);
            S_out(0) <= SR_in_R;
            SR_out_L <= A_in(3);
            SR_out_R <= '0';
            when "1010" => -- S = Right shift B (avec SR_IN_L)
            S_out(2 downto 0) <= B_in(3 downto 1);
            S_out(3) <= SR_in_L;
            SR_out_R <= B_in(0);
            SR_out_L <= '0';            
            when "1011" => -- S = Left shift B (avec SR_IN_R)
            S_out(3 downto 1) <= B_in(2 downto 0);
            S_out(0) <= SR_in_R;
            SR_out_L <= B_in(3);
            SR_out_R <= '0';
            when "1100" => -- S = A * B
            S_out <= std_logic_vector(unsigned(A_in) * unsigned(B_in));
            SR_out_L <= '0';
            SR_out_R <= '0';
            when "1101" => -- S = A + B with SR_IN_R as carry in
            if SR_in_R = '1' then
                S_out(3 downto 0) <= std_logic_vector(unsigned(A_in) + unsigned(B_in) + 1);
                if to_integer(unsigned(A_in)) + to_integer(unsigned(B_in)) > 14 then
                    S_out(4) <= '1';
                end if;
            else
                S_out(3 downto 0) <= std_logic_vector(unsigned(A_in) + unsigned(B_in));
                if to_integer(unsigned(A_in)) + to_integer(unsigned(B_in)) > 14 then
                    S_out(4) <= '1';
                end if;
            end if;
            SR_out_L <= '0';
            SR_out_R <= '0';
            when "1110" => -- S = A + B without carry in
            S_out(3 downto 0) <= std_logic_vector(unsigned(A_in) + unsigned(B_in));
            if to_integer(unsigned(A_in)) + to_integer(unsigned(B_in))> 15 then
                S_out(4) <= '1';
            end if;
            SR_out_L <= '0';
            SR_out_R <= '0';
            when "1111" => -- S = A - B
            S_out(3 downto 0) <= std_logic_vector(unsigned(A_in) - unsigned(B_in));
            if unsigned(A_in) < unsigned(B_in) then
                S_out(4) <= '1';
            end if;
            SR_out_L <= '0';
            SR_out_R <= '0';
            when others =>
            S_out <= (others => '0');
            SR_out_L <= '0';
            SR_out_R <= '0';
        end case;
    end process;
end ual_dataflow;

project/testbenchual.vhd
library IEEE;
use IEEE.std_logic_1164.all;
use IEEE.numeric_std.all;
use IEEE.std_logic_unsigned.all;

entity ualtestbench is
end ualtestbench;

architecture ualtestbench_arch of ualtestbench is
    component ual
    port (
        A_in: in std_logic_vector(3 downto 0);
        B_in: in std_logic_vector(3 downto 0);
        SR_in_L: in std_logic;
        SR_in_R: in std_logic;
        SEL_FCT: in std_logic_vector(3 downto 0);
        SR_out_L: out std_logic;
        SR_out_R: out std_logic;
        S_out: out std_logic_vector(7 downto 0)
    );
    end component;

    signal A_in_sim, B_in_sim: std_logic_vector(3 downto 0) := (others => '0');
    signal SR_in_L_sim, SR_in_R_sim, SR_out_L_sim, SR_out_R_sim: std_logic := '0';
    signal SEL_FCT_sim: std_logic_vector(3 downto 0) := (others => '0');
    signal S_out_sim: std_logic_vector(7 downto 0) := (others => '0');

begin  
    ual1: ual
    port map(
        A_in => A_in_sim,
        B_in => B_in_sim,
        SR_in_L => SR_in_L_sim,
        SR_in_R => SR_in_R_sim,
        SEL_FCT => SEL_FCT_sim,
        SR_out_L => SR_out_L_sim,
        SR_out_R => SR_out_R_sim,
        S_out => S_out_sim
    );
    
    myprocess: process
    begin
        A_in_sim <= "0010";
        B_in_sim <= "1110";
        SR_in_L_sim <= '1';
        SR_in_R_sim <= '1';
        for i in 0 to 15 loop
            SEL_FCT_sim <= std_logic_vector(to_unsigned(i, 4));
            for j in 0 to 15 loop
                A_in_sim <= std_logic_vector(to_unsigned(j, 4));
                wait for 10 ns;
            end loop;
            wait for 10 ns;
        end loop;
        wait;
    end process myprocess;
end ualtestbench_arch;

project/testbench.vcd
$date
  Wed Mar 22 20:35:04 2023
$end
$version
  GHDL v0
$end
$timescale
  1 fs
$end
$scope module standard $end
$upscope $end
$scope module std_logic_1164 $end
$upscope $end
$scope module numeric_std $end
$upscope $end
$scope module std_logic_arith $end
$upscope $end
$scope module std_logic_unsigned $end
$upscope $end
$scope module ualtestbench $end
$var reg 4 ! a_in_sim[3:0] $end
$var reg 4 " b_in_sim[3:0] $end
$var reg 1 # sr_in_l_sim $end
$var reg 1 $ sr_in_r_sim $end
$var reg 1 % sr_out_l_sim $end
$var reg 1 & sr_out_r_sim $end
$var reg 4 ' sel_fct_sim[3:0] $end
$var reg 8 ( s_out_sim[7:0] $end
$scope module ual1 $end
$var reg 4 ) a_in[3:0] $end
$var reg 4 * b_in[3:0] $end
$var reg 1 + sr_in_l $end
$var reg 1 , sr_in_r $end
$var reg 4 - sel_fct[3:0] $end
$var reg 1 . sr_out_l $end
$var reg 1 / sr_out_r $end
$var reg 8 0 s_out[7:0] $end
$upscope $end
$upscope $end
$enddefinitions $end
#0
b0000 !
b1110 "
1#
1$
0%
0&
b0000 '
b00000000 (
b0000 )
b1110 *
1+
1,
b0000 -
0.
0/
b00000000 0
#10000000
b0001 !
b0001 )
#20000000
b0010 !
b0010 )
#30000000
b0011 !
b0011 )
#40000000
b0100 !
b0100 )
#50000000
b0101 !
b0101 )
#60000000
b0110 !
b0110 )
#70000000
b0111 !
b0111 )
#80000000
b1000 !
b1000 )
#90000000
b1001 !
b1001 )
#100000000
b1010 !
b1010 )
#110000000
b1011 !
b1011 )
#120000000
b1100 !
b1100 )
#130000000
b1101 !
b1101 )
#140000000
b1110 !
b1110 )
#150000000
b1111 !
b1111 )
#160000000
#170000000
b0000 !
b0001 '
b0000 )
b0001 -
#180000000
b0001 !
b00000001 (
b0001 )
b00000001 0
#190000000
b0010 !
b00000010 (
b0010 )
b00000010 0
#200000000
b0011 !
b00000011 (
b0011 )
b00000011 0
#210000000
b0100 !
b00000100 (
b0100 )
b00000100 0
#220000000
b0101 !
b00000101 (
b0101 )
b00000101 0
#230000000
b0110 !
b00000110 (
b0110 )
b00000110 0
#240000000
b0111 !
b00000111 (
b0111 )
b00000111 0
#250000000
b1000 !
b00001000 (
b1000 )
b00001000 0
#260000000
b1001 !
b00001001 (
b1001 )
b00001001 0
#270000000
b1010 !
b00001010 (
b1010 )
b00001010 0
#280000000
b1011 !
b00001011 (
b1011 )
b00001011 0
#290000000
b1100 !
b00001100 (
b1100 )
b00001100 0
#300000000
b1101 !
b00001101 (
b1101 )
b00001101 0
#310000000
b1110 !
b00001110 (
b1110 )
b00001110 0
#320000000
b1111 !
b00001111 (
b1111 )
b00001111 0
#330000000
#340000000
b0000 !
b0010 '
b00001110 (
b0000 )
b0010 -
b00001110 0
#350000000
b0001 !
b0001 )
b00001110 0
#360000000
b0010 !
b0010 )
b00001110 0
#370000000
b0011 !
b0011 )
b00001110 0
#380000000
b0100 !
b0100 )
b00001110 0
#390000000
b0101 !
b0101 )
b00001110 0
#400000000
b0110 !
b0110 )
b00001110 0
#410000000
b0111 !
b0111 )
b00001110 0
#420000000
b1000 !
b1000 )
b00001110 0
#430000000
b1001 !
b1001 )
b00001110 0
#440000000
b1010 !
b1010 )
b00001110 0
#450000000
b1011 !
b1011 )
b00001110 0
#460000000
b1100 !
b1100 )
b00001110 0
#470000000
b1101 !
b1101 )
b00001110 0
#480000000
b1110 !
b1110 )
b00001110 0
#490000000
b1111 !
b1111 )
b00001110 0
#500000000
#510000000
b0000 !
b0011 '
b00001111 (
b0000 )
b0011 -
b00001111 0
#520000000
b0001 !
b00001110 (
b0001 )
b00001110 0
#530000000
b0010 !
b00001101 (
b0010 )
b00001101 0
#540000000
b0011 !
b00001100 (
b0011 )
b00001100 0
#550000000
b0100 !
b00001011 (
b0100 )
b00001011 0
#560000000
b0101 !
b00001010 (
b0101 )
b00001010 0
#570000000
b0110 !
b00001001 (
b0110 )
b00001001 0
#580000000
b0111 !
b00001000 (
b0111 )
b00001000 0
#590000000
b1000 !
b00000111 (
b1000 )
b00000111 0
#600000000
b1001 !
b00000110 (
b1001 )
b00000110 0
#610000000
b1010 !
b00000101 (
b1010 )
b00000101 0
#620000000
b1011 !
b00000100 (
b1011 )
b00000100 0
#630000000
b1100 !
b00000011 (
b1100 )
b00000011 0
#640000000
b1101 !
b00000010 (
b1101 )
b00000010 0
#650000000
b1110 !
b00000001 (
b1110 )
b00000001 0
#660000000
b1111 !
b00000000 (
b1111 )
b00000000 0
#670000000
#680000000
b0000 !
b0100 '
b00000001 (
b0000 )
b0100 -
b00000001 0
#690000000
b0001 !
b0001 )
b00000001 0
#700000000
b0010 !
b0010 )
b00000001 0
#710000000
b0011 !
b0011 )
b00000001 0
#720000000
b0100 !
b0100 )
b00000001 0
#730000000
b0101 !
b0101 )
b00000001 0
#740000000
b0110 !
b0110 )
b00000001 0
#750000000
b0111 !
b0111 )
b00000001 0
#760000000
b1000 !
b1000 )
b00000001 0
#770000000
b1001 !
b1001 )
b00000001 0
#780000000
b1010 !
b1010 )
b00000001 0
#790000000
b1011 !
b1011 )
b00000001 0
#800000000
b1100 !
b1100 )
b00000001 0
#810000000
b1101 !
b1101 )
b00000001 0
#820000000
b1110 !
b1110 )
b00000001 0
#830000000
b1111 !
b1111 )
b00000001 0
#840000000
#850000000
b0000 !
b0101 '
b00000000 (
b0000 )
b0101 -
b00000000 0
#860000000
b0001 !
b0001 )
#870000000
b0010 !
b00000010 (
b0010 )
b00000010 0
#880000000
b0011 !
b0011 )
b00000010 0
#890000000
b0100 !
b00000100 (
b0100 )
b00000100 0
#900000000
b0101 !
b0101 )
b00000100 0
#910000000
b0110 !
b00000110 (
b0110 )
b00000110 0
#920000000
b0111 !
b0111 )
b00000110 0
#930000000
b1000 !
b00001000 (
b1000 )
b00001000 0
#940000000
b1001 !
b1001 )
b00001000 0
#950000000
b1010 !
b00001010 (
b1010 )
b00001010 0
#960000000
b1011 !
b1011 )
b00001010 0
#970000000
b1100 !
b00001100 (
b1100 )
b00001100 0
#980000000
b1101 !
b1101 )
b00001100 0
#990000000
b1110 !
b00001110 (
b1110 )
b00001110 0
#1000000000
b1111 !
b1111 )
b00001110 0
#1010000000
#1020000000
b0000 !
b0110 '
b0000 )
b0110 -
b00001110 0
#1030000000
b0001 !
b00001111 (
b0001 )
b00001111 0
#1040000000
b0010 !
b00001110 (
b0010 )
b00001110 0
#1050000000
b0011 !
b00001111 (
b0011 )
b00001111 0
#1060000000
b0100 !
b00001110 (
b0100 )
b00001110 0
#1070000000
b0101 !
b00001111 (
b0101 )
b00001111 0
#1080000000
b0110 !
b00001110 (
b0110 )
b00001110 0
#1090000000
b0111 !
b00001111 (
b0111 )
b00001111 0
#1100000000
b1000 !
b00001110 (
b1000 )
b00001110 0
#1110000000
b1001 !
b00001111 (
b1001 )
b00001111 0
#1120000000
b1010 !
b00001110 (
b1010 )
b00001110 0
#1130000000
b1011 !
b00001111 (
b1011 )
b00001111 0
#1140000000
b1100 !
b00001110 (
b1100 )
b00001110 0
#1150000000
b1101 !
b00001111 (
b1101 )
b00001111 0
#1160000000
b1110 !
b00001110 (
b1110 )
b00001110 0
#1170000000
b1111 !
b00001111 (
b1111 )
b00001111 0
#1180000000
#1190000000
b0000 !
b0111 '
b00001110 (
b0000 )
b0111 -
b00001110 0
#1200000000
b0001 !
b00001111 (
b0001 )
b00001111 0
#1210000000
b0010 !
b00001100 (
b0010 )
b00001100 0
#1220000000
b0011 !
b00001101 (
b0011 )
b00001101 0
#1230000000
b0100 !
b00001010 (
b0100 )
b00001010 0
#1240000000
b0101 !
b00001011 (
b0101 )
b00001011 0
#1250000000
b0110 !
b00001000 (
b0110 )
b00001000 0
#1260000000
b0111 !
b00001001 (
b0111 )
b00001001 0
#1270000000
b1000 !
b00000110 (
b1000 )
b00000110 0
#1280000000
b1001 !
b00000111 (
b1001 )
b00000111 0
#1290000000
b1010 !
b00000100 (
b1010 )
b00000100 0
#1300000000
b1011 !
b00000101 (
b1011 )
b00000101 0
#1310000000
b1100 !
b00000010 (
b1100 )
b00000010 0
#1320000000
b1101 !
b00000011 (
b1101 )
b00000011 0
#1330000000
b1110 !
b00000000 (
b1110 )
b00000000 0
#1340000000
b1111 !
b00000001 (
b1111 )
b00000001 0
#1350000000
#1360000000
b0000 !
1%
b1000 '
b00000000 (
b0000 )
b1000 -
1.
b00000000 0
#1370000000
b0001 !
1&
b0001 )
1/
#1380000000
b0010 !
0&
b00000001 (
b0010 )
0/
b00000001 0
#1390000000
b0011 !
1&
b0011 )
1/
b00000001 0
#1400000000
b0100 !
0&
b00000010 (
b0100 )
0/
b00000010 0
#1410000000
b0101 !
1&
b0101 )
1/
b00000010 0
#1420000000
b0110 !
0&
b00000011 (
b0110 )
0/
b00000011 0
#1430000000
b0111 !
1&
b0111 )
1/
b00000011 0
#1440000000
b1000 !
0&
b00000100 (
b1000 )
0/
b00000100 0
#1450000000
b1001 !
1&
b1001 )
1/
b00000100 0
#1460000000
b1010 !
0&
b00000101 (
b1010 )
0/
b00000101 0
#1470000000
b1011 !
1&
b1011 )
1/
b00000101 0
#1480000000
b1100 !
0&
b00000110 (
b1100 )
0/
b00000110 0
#1490000000
b1101 !
1&
b1101 )
1/
b00000110 0
#1500000000
b1110 !
0&
b00000111 (
b1110 )
0/
b00000111 0
#1510000000
b1111 !
1&
b1111 )
1/
b00000111 0
#1520000000
#1530000000
b0000 !
0%
0&
b1001 '
b00000001 (
b0000 )
b1001 -
0.
0/
b00000001 0
#1540000000
b0001 !
b00000011 (
b0001 )
b00000011 0
#1550000000
b0010 !
b00000101 (
b0010 )
b00000101 0
#1560000000
b0011 !
b00000111 (
b0011 )
b00000111 0
#1570000000
b0100 !
b00001001 (
b0100 )
b00001001 0
#1580000000
b0101 !
b00001011 (
b0101 )
b00001011 0
#1590000000
b0110 !
b00001101 (
b0110 )
b00001101 0
#1600000000
b0111 !
b00001111 (
b0111 )
b00001111 0
#1610000000
b1000 !
1%
b00000001 (
b1000 )
1.
b00000001 0
#1620000000
b1001 !
b00000011 (
b1001 )
b00000011 0
#1630000000
b1010 !
b00000101 (
b1010 )
b00000101 0
#1640000000
b1011 !
b00000111 (
b1011 )
b00000111 0
#1650000000
b1100 !
b00001001 (
b1100 )
b00001001 0
#1660000000
b1101 !
b00001011 (
b1101 )
b00001011 0
#1670000000
b1110 !
b00001101 (
b1110 )
b00001101 0
#1680000000
b1111 !
b00001111 (
b1111 )
b00001111 0
#1690000000
#1700000000
b0000 !
0%
b1010 '
b0000 )
b1010 -
0.
b00001111 0
#1710000000
b0001 !
b0001 )
b00001111 0
#1720000000
b0010 !
b0010 )
b00001111 0
#1730000000
b0011 !
b0011 )
b00001111 0
#1740000000
b0100 !
b0100 )
b00001111 0
#1750000000
b0101 !
b0101 )
b00001111 0
#1760000000
b0110 !
b0110 )
b00001111 0
#1770000000
b0111 !
b0111 )
b00001111 0
#1780000000
b1000 !
b1000 )
b00001111 0
#1790000000
b1001 !
b1001 )
b00001111 0
#1800000000
b1010 !
b1010 )
b00001111 0
#1810000000
b1011 !
b1011 )
b00001111 0
#1820000000
b1100 !
b1100 )
b00001111 0
#1830000000
b1101 !
b1101 )
b00001111 0
#1840000000
b1110 !
b1110 )
b00001111 0
#1850000000
b1111 !
b1111 )
b00001111 0
#1860000000
#1870000000
b0000 !
1%
b1011 '
b00001101 (
b0000 )
b1011 -
1.
b00001101 0
#1880000000
b0001 !
b0001 )
b00001101 0
#1890000000
b0010 !
b0010 )
b00001101 0
#1900000000
b0011 !
b0011 )
b00001101 0
#1910000000
b0100 !
b0100 )
b00001101 0
#1920000000
b0101 !
b0101 )
b00001101 0
#1930000000
b0110 !
b0110 )
b00001101 0
#1940000000
b0111 !
b0111 )
b00001101 0
#1950000000
b1000 !
b1000 )
b00001101 0
#1960000000
b1001 !
b1001 )
b00001101 0
#1970000000
b1010 !
b1010 )
b00001101 0
#1980000000
b1011 !
b1011 )
b00001101 0
#1990000000
b1100 !
b1100 )
b00001101 0
#2000000000
b1101 !
b1101 )
b00001101 0
#2010000000
b1110 !
b1110 )
b00001101 0
#2020000000
b1111 !
b1111 )
b00001101 0
#2030000000
#2040000000
b0000 !
0%
b1100 '
b00000000 (
b0000 )
b1100 -
0.
b00000000 0
#2050000000
b0001 !
b00001110 (
b0001 )
b00001110 0
#2060000000
b0010 !
b00011100 (
b0010 )
b00011100 0
#2070000000
b0011 !
b00101010 (
b0011 )
b00101010 0
#2080000000
b0100 !
b00111000 (
b0100 )
b00111000 0
#2090000000
b0101 !
b01000110 (
b0101 )
b01000110 0
#2100000000
b0110 !
b01010100 (
b0110 )
b01010100 0
#2110000000
b0111 !
b01100010 (
b0111 )
b01100010 0
#2120000000
b1000 !
b01110000 (
b1000 )
b01110000 0
#2130000000
b1001 !
b01111110 (
b1001 )
b01111110 0
#2140000000
b1010 !
b10001100 (
b1010 )
b10001100 0
#2150000000
b1011 !
b10011010 (
b1011 )
b10011010 0
#2160000000
b1100 !
b10101000 (
b1100 )
b10101000 0
#2170000000
b1101 !
b10110110 (
b1101 )
b10110110 0
#2180000000
b1110 !
b11000100 (
b1110 )
b11000100 0
#2190000000
b1111 !
b11010010 (
b1111 )
b11010010 0
#2200000000
#2210000000
b0000 !
b1101 '
b00001111 (
b0000 )
b1101 -
b00001111 0
#2220000000
b0001 !
b00010000 (
b0001 )
b00010000 0
#2230000000
b0010 !
b00010001 (
b0010 )
b00010001 0
#2240000000
b0011 !
b00010010 (
b0011 )
b00010010 0
#2250000000
b0100 !
b00010011 (
b0100 )
b00010011 0
#2260000000
b0101 !
b00010100 (
b0101 )
b00010100 0
#2270000000
b0110 !
b00010101 (
b0110 )
b00010101 0
#2280000000
b0111 !
b00010110 (
b0111 )
b00010110 0
#2290000000
b1000 !
b00010111 (
b1000 )
b00010111 0
#2300000000
b1001 !
b00011000 (
b1001 )
b00011000 0
#2310000000
b1010 !
b00011001 (
b1010 )
b00011001 0
#2320000000
b1011 !
b00011010 (
b1011 )
b00011010 0
#2330000000
b1100 !
b00011011 (
b1100 )
b00011011 0
#2340000000
b1101 !
b00011100 (
b1101 )
b00011100 0
#2350000000
b1110 !
b00011101 (
b1110 )
b00011101 0
#2360000000
b1111 !
b00011110 (
b1111 )
b00011110 0
#2370000000
#2380000000
b0000 !
b1110 '
b00001110 (
b0000 )
b1110 -
b00001110 0
#2390000000
b0001 !
b00001111 (
b0001 )
b00001111 0
#2400000000
b0010 !
b00010000 (
b0010 )
b00010000 0
#2410000000
b0011 !
b00010001 (
b0011 )
b00010001 0
#2420000000
b0100 !
b00010010 (
b0100 )
b00010010 0
#2430000000
b0101 !
b00010011 (
b0101 )
b00010011 0
#2440000000
b0110 !
b00010100 (
b0110 )
b00010100 0
#2450000000
b0111 !
b00010101 (
b0111 )
b00010101 0
#2460000000
b1000 !
b00010110 (
b1000 )
b00010110 0
#2470000000
b1001 !
b00010111 (
b1001 )
b00010111 0
#2480000000
b1010 !
b00011000 (
b1010 )
b00011000 0
#2490000000
b1011 !
b00011001 (
b1011 )
b00011001 0
#2500000000
b1100 !
b00011010 (
b1100 )
b00011010 0
#2510000000
b1101 !
b00011011 (
b1101 )
b00011011 0
#2520000000
b1110 !
b00011100 (
b1110 )
b00011100 0
#2530000000
b1111 !
b00011101 (
b1111 )
b00011101 0
#2540000000
#2550000000
b0000 !
b1111 '
b00010010 (
b0000 )
b1111 -
b00010010 0
#2560000000
b0001 !
b00010011 (
b0001 )
b00010011 0
#2570000000
b0010 !
b00010100 (
b0010 )
b00010100 0
#2580000000
b0011 !
b00010101 (
b0011 )
b00010101 0
#2590000000
b0100 !
b00010110 (
b0100 )
b00010110 0
#2600000000
b0101 !
b00010111 (
b0101 )
b00010111 0
#2610000000
b0110 !
b00011000 (
b0110 )
b00011000 0
#2620000000
b0111 !
b00011001 (
b0111 )
b00011001 0
#2630000000
b1000 !
b00011010 (
b1000 )
b00011010 0
#2640000000
b1001 !
b00011011 (
b1001 )
b00011011 0
#2650000000
b1010 !
b00011100 (
b1010 )
b00011100 0
#2660000000
b1011 !
b00011101 (
b1011 )
b00011101 0
#2670000000
b1100 !
b00011110 (
b1100 )
b00011110 0
#2680000000
b1101 !
b00011111 (
b1101 )
b00011111 0
#2690000000
b1110 !
b00000000 (
b1110 )
b00000000 0
#2700000000
b1111 !
b00000001 (
b1111 )
b00000001 0
