project/design/buffer.vhd
library IEEE ;
use IEEE.std_logic_1164.all ;

entity bufferNbits is
generic (
	N : integer :=4
);
port(
	e1 : in std_logic_vector (N-1 downto 0);
	reset : in std_logic;
	preset : in std_logic;
	clock : in std_logic;
	s1 : out std_logic_vector (N-1 downto 0)
);
end bufferNbits;

architecture bufferNbits_Arch of bufferNbits is

begin

	MyBufferNbitsProc : process (reset, clock)
	begin
		if (reset = '1') then
			s1 <= (others => '0');
		elsif (rising_edge(clock)) then
			if (preset = '1') then
				s1 <= (others => '1');
			else
				s1 <= e1;
			end if;
		end if;
	end process;

end bufferNbits_Arch;

project/testbenchbuffer.vhd
Library IEEE ;
use IEEE.std_logic_1164.all ;
use IEEE.numeric_std.all ;

--Déclaration d'une entité pour la simulation sans ports d'entrées et de sorties
entity mybufferNbitstestbench is

end mybufferNbitstestbench;

architecture mybufferNbitstestbench_Arch of mybufferNbitstestbench is
	component bufferNbits is
	generic (N : integer );
	port(
		e1 : in std_logic_vector (N-1 downto 0);
		reset : in std_logic;
		preset : in std_logic;
		clock : in std_logic;
		s1 : out std_logic_vector (N-1 downto 0)
	);
	end component;

	constant N : integer := 3;

    constant PERIOD : time := 50 us;

	signal e1_sim : std_logic_vector(N-1 downto 0) := (others => '0');
	signal s1_sim : std_logic_vector(N-1 downto 0) := (others => '0');
	signal reset_sim, preset_sim, clock_sim : std_logic := '0';

begin

	MyComponentsynthcombo1underTest : bufferNbits
	generic map(N =>N)
	port map (
		e1 => e1_sim,
		reset => reset_sim,
		preset => preset_sim,
		clock => clock_sim,
		s1 => s1_sim
	);
    My_Clock_Proc: process
    begin 
        clock_sim <= '0';
        wait for PERIOD/2;
        clock_sim <= '1';
        wait for PERIOD/2;
    end process;

    MyStimulus_Proc2: process
    begin
        for i in 0 to (2**N)-1 loop
            e1_sim <= std_logic_vector(to_unsigned(i,N));
            wait for PERIOD;
        end loop;
        for i in 0 to (2**N)-1 loop
            e1_sim <= std_logic_vector(to_unsigned(i,N));
            wait for PERIOD;
        end loop;
        wait;
    end process;
    My_Reset_Proc: process
    begin
        wait for 234 us;
        reset_sim <= '1';
        wait for 150 us;
        reset_sim <= '0';
        wait;
    end process;
    My_Preset_Proc: process
    begin
        wait for 610 us;
        preset_sim <= '1';
        wait for 150 us;
        preset_sim <= '0';
        wait;
    end process;
end mybufferNbitstestbench_Arch;

project/testbench.vcd
$date
  Thu Mar 23 17:25:50 2023
$end
$version
  GHDL v0
$end
$timescale
  1 fs
$end
$scope module standard $end
$upscope $end
$scope module std_logic_1164 $end
$upscope $end
$scope module numeric_std $end
$upscope $end
$scope module mybuffernbitstestbench $end
$var reg 3 ! e1_sim[2:0] $end
$var reg 3 " s1_sim[2:0] $end
$var reg 1 # reset_sim $end
$var reg 1 $ preset_sim $end
$var reg 1 % clock_sim $end
$scope module mycomponentsynthcombo1undertest $end
$var reg 3 & e1[2:0] $end
$var reg 1 ' reset $end
$var reg 1 ( preset $end
$var reg 1 ) clock $end
$var reg 3 * s1[2:0] $end
$upscope $end
$upscope $end
$enddefinitions $end
#0
b000 !
bUUU "
0#
0$
0%
b000 &
0'
0(
0)
bUUU *
#25000000000
b000 "
1%
1)
b000 *
#50000000000
b001 !
0%
b001 &
0)
#75000000000
b001 "
1%
1)
b001 *
#100000000000
b010 !
0%
b010 &
0)
#125000000000
b010 "
1%
1)
b010 *
#150000000000
b011 !
0%
b011 &
0)
#175000000000
b011 "
1%
1)
b011 *
#200000000000
b100 !
0%
b100 &
0)
#225000000000
b100 "
1%
1)
b100 *
#234000000000
b000 "
1#
1'
b000 *
#250000000000
b101 !
0%
b101 &
0)
#275000000000
1%
1)
#300000000000
b110 !
0%
b110 &
0)
#325000000000
1%
1)
#350000000000
b111 !
0%
b111 &
0)
#375000000000
1%
1)
#384000000000
0#
0'
#400000000000
b000 !
0%
b000 &
0)
#425000000000
1%
1)
#450000000000
b001 !
0%
b001 &
0)
#475000000000
b001 "
1%
1)
b001 *
#500000000000
b010 !
0%
b010 &
0)
#525000000000
b010 "
1%
1)
b010 *
#550000000000
b011 !
0%
b011 &
0)
#575000000000
b011 "
1%
1)
b011 *
#600000000000
b100 !
0%
b100 &
0)
#610000000000
1$
1(
#625000000000
b111 "
1%
1)
b111 *
#650000000000
b101 !
0%
b101 &
0)
#675000000000
1%
1)
#700000000000
b110 !
0%
b110 &
0)
#725000000000
1%
1)
#750000000000
b111 !
0%
b111 &
0)
#760000000000
0$
0(
